{"stats":{"minecraft:custom":{"minecraft:time_since_rest":252808,"minecraft:sprint_one_cm":216213,"minecraft:damage_taken":110,"minecraft:walk_one_cm":355771,"minecraft:drop":24,"minecraft:swim_one_cm":1057,"minecraft:fly_one_cm":10120696,"minecraft:open_chest":1,"minecraft:crouch_one_cm":18424,"minecraft:play_time":252808,"minecraft:sneak_time":9249,"minecraft:walk_under_water_one_cm":430,"minecraft:jump":1022,"minecraft:leave_game":8,"minecraft:time_since_death":252808,"minecraft:walk_on_water_one_cm":3357,"minecraft:total_world_time":252808,"minecraft:climb_one_cm":223,"minecraft:fall_one_cm":1487},"minecraft:picked_up":{"minecraft:wooden_axe":1,"minecraft:light_blue_concrete":2,"minecraft:lily_pad":2,"minecraft:polished_andesite":1,"minecraft:stone_bricks":1},"minecraft:used":{"minecraft:lever":4,"minecraft:black_concrete":35,"minecraft:polished_deepslate":17,"minecraft:snow_block":1,"minecraft:red_wool":2,"minecraft:light_gray_concrete":1,"minecraft:grass_block":27,"minecraft:polished_andesite":1,"minecraft:cyan_concrete":4,"minecraft:stone":1,"minecraft:spruce_trapdoor":3,"minecraft:redstone_block":7,"minecraft:stone_bricks":959,"minecraft:cracked_stone_bricks":1,"minecraft:light_gray_wool":1,"minecraft:chiseled_stone_bricks":1,"minecraft:dark_oak_trapdoor":2,"minecraft:light_blue_concrete":5,"minecraft:gray_glazed_terracotta":456,"minecraft:birch_log":2,"minecraft:light_gray_glazed_terracotta":8,"minecraft:acacia_wood":1,"minecraft:light_gray_concrete_powder":5,"minecraft:tuff":1,"minecraft:air":6870,"minecraft:stone_brick_wall":1,"minecraft:spruce_log":1,"minecraft:smooth_stone":130,"minecraft:stripped_spruce_wood":1},"minecraft:dropped":{"minecraft:cyan_terracotta":64,"minecraft:deepslate_tiles":1,"minecraft:stone":1,"minecraft:green_terracotta":64,"minecraft:orange_terracotta":256,"minecraft:gray_glazed_terracotta":1,"minecraft:wooden_axe":1,"minecraft:yellow_terracotta":128,"minecraft:stone_bricks":1,"minecraft:black_concrete":1,"minecraft:red_terracotta":64,"minecraft:light_blue_concrete":3,"minecraft:lily_pad":3,"minecraft:polished_andesite":1,"minecraft:polished_deepslate":1,"minecraft:deepslate_bricks":1}},"DataVersion":3578}