{"stats":{"minecraft:custom":{"minecraft:time_since_rest":41912,"minecraft:crouch_one_cm":206,"minecraft:play_time":41912,"minecraft:sprint_one_cm":421,"minecraft:walk_one_cm":6803,"minecraft:damage_taken":50,"minecraft:sneak_time":305,"minecraft:drop":5,"minecraft:jump":6,"minecraft:leave_game":1,"minecraft:time_since_death":41912,"minecraft:total_world_time":249704,"minecraft:fall_one_cm":335,"minecraft:fly_one_cm":136386},"minecraft:dropped":{"minecraft:brown_carpet":1,"minecraft:oak_wood":1,"minecraft:oak_sign":1,"minecraft:grass_block":1,"minecraft:carrot_on_a_stick":1},"minecraft:used":{"minecraft:brown_carpet":1,"minecraft:spruce_door":1,"minecraft:grass_block":2,"minecraft:carrot_on_a_stick":2,"minecraft:oak_sign":2,"minecraft:oak_wood":1}},"DataVersion":3805}